TheRockTrading/__init__.py
TheRockTrading/client_async.py
TheRockTrading/client_sync.py
TheRockTrading/config_async.py
TheRockTrading/config_sync.py
TheRockTrading/generic_config.py
TheRockTrading/t.py
py_therocktrading_api-1.1.4.dist-info/LICENSE
py_therocktrading_api-1.1.4.dist-info/METADATA
py_therocktrading_api-1.1.4.dist-info/WHEEL
py_therocktrading_api-1.1.4.dist-info/top_level.txt
py_therocktrading_api-1.1.4.dist-info/RECORD
