Metadata-Version: 2.1
Name: py-therocktrading-api
Version: 1.1.4
Summary: Official TheRockTrading Python Library to comunicate with JSON REST API
Home-page: https://github.com/therocktrading/py-therocktrading-api
Author: Andrea Previtali
Author-email: ipergiove@duck.com
Project-URL: Doc, https://api.therocktrading.com/doc
Project-URL: Source, https://github.com/therocktrading/py-therocktrading-api
Keywords: TheRockTrading,api,trading,trt
Classifier: Development Status :: 5 - Production/Stable
Classifier: Intended Audience :: Developers
Classifier: Topic :: Software Development :: Build Tools
Classifier: License :: OSI Approved :: Apache Software License
Classifier: Programming Language :: Python :: 3.0
Classifier: Programming Language :: Python :: 3.2
Classifier: Programming Language :: Python :: 3.3
Classifier: Programming Language :: Python :: 3.4
Classifier: Programming Language :: Python :: 3.5
Classifier: Programming Language :: Python :: 3.6
Classifier: Programming Language :: Python :: 3.7
Classifier: Programming Language :: Python :: 3.8
Classifier: Programming Language :: Python :: 3.9
Requires-Python: >=3.0.0, <4
License-File: LICENSE
Requires-Dist: httpx (~=0.21.1)
Requires-Dist: aiohttp (~=3.8.1)
